tests
flutterwave
