Metadata-Version: 1.1
Name: Flutterwave
Version: 1.0.5
Summary: Flutterwave
Home-page: https://github.com/Flutterwave/flutterwave-python
Author: Obinna Isintume
Author-email: ibonobij@gmail
License: UNKNOWN
Keywords: Payments,Payment-integration,Payment-API,Flutterwave
Platform: UNKNOWN
Classifier: Development Status :: 5 - Production/Stable
Classifier: Intended Audience :: Developers
Classifier: Intended Audience :: Other Audience
Classifier: Topic :: Software Development :: Libraries :: Python Modules
